LICENSE
MANIFEST.in
README.rst
requirements.txt
setup.py
zhihuapi/__init__.py
zhihuapi/action.py
zhihuapi/answer.py
zhihuapi/collection.py
zhihuapi/column.py
zhihuapi/question.py
zhihuapi/request.py
zhihuapi/topic.py
zhihuapi/urls.py
zhihuapi/user.py
zhihuapi.egg-info/PKG-INFO
zhihuapi.egg-info/SOURCES.txt
zhihuapi.egg-info/dependency_links.txt
zhihuapi.egg-info/not-zip-safe
zhihuapi.egg-info/requires.txt
zhihuapi.egg-info/top_level.txt
zhihuapi/parser/__init__.py
zhihuapi/parser/answer.py
zhihuapi/parser/collection.py
zhihuapi/parser/question.py
zhihuapi/parser/topic.py
zhihuapi/parser/user.py
zhihuapi/parser/util.py