Metadata-Version: 1.1
Name: zhihuapi
Version: 0.5.0
Summary: Unofficial API for zhihu.
Home-page: https://github.com/syaning/zhihuapi-py
Author: Alex Sun
Author-email: syaningv@gmail.com
License: MIT
Keywords: zhihuapi zhihu api crawler spider
Platform: UNKNOWN
Classifier: Development Status :: 3 - Alpha
Classifier: License :: OSI Approved :: MIT License
Classifier: Programming Language :: Python :: 3
Classifier: Programming Language :: Python :: 3.3
Classifier: Programming Language :: Python :: 3.4
Classifier: Programming Language :: Python :: 3.5
Classifier: Programming Language :: Python :: 3 :: Only
